common/__init__.py
common/constants.py
core/EditableTreeData.py
core/ExtendedTree.py
core/TreeNode.py
core/__init__.py
forms/AddExampleForm.py
forms/AddItemForm.py
forms/AddStoryItemForm.py
forms/RemoveItemForm.py
forms/UpdateItemForm.py
forms/__init__.py
gui/__init__.py
gui/layout.py
gui/run.py
handlers/Exporter.py
handlers/Handler.py
handlers/NLUHandler.py
handlers/ResponseHandler.py
handlers/StoriesHandler.py
handlers/__init__.py
rasa_storyteller-0.1.dist-info/LICENSE
rasa_storyteller-0.1.dist-info/METADATA
rasa_storyteller-0.1.dist-info/WHEEL
rasa_storyteller-0.1.dist-info/entry_points.txt
rasa_storyteller-0.1.dist-info/top_level.txt
rasa_storyteller-0.1.dist-info/RECORD
