Metadata-Version: 2.1
Name: rasa-storyteller
Version: 0.1
Summary: A simple GUI utility to create complex stories for RASA chatbots easily.
Home-page: https://github.com/Ezhvsalate/rasa-storyteller
Author: ezhvsalate
Author-email: ezhvsalate@ya.ru
License: UNKNOWN
Platform: UNKNOWN
Classifier: Programming Language :: Python :: 3
Classifier: License :: OSI Approved :: MIT License
Classifier: Operating System :: OS Independent
Requires-Python: >=3.6
Requires-Dist: PySimpleGUI (==4.16.0)
Requires-Dist: markdown-generator (==0.1.3)
Requires-Dist: PyYAML (==5.3.1)
Requires-Dist: Pillow (==7.0.0)
